neural_admixture-1.6.7.dist-info/RECORD
neural_admixture-1.6.7.dist-info/WHEEL
neural_admixture-1.6.7.dist-info/entry_points.txt
neural_admixture-1.6.7.dist-info/top_level.txt
neural_admixture-1.6.7.dist-info/METADATA
neural_admixture/_version.py
neural_admixture/__init__.py
neural_admixture/entry.py
neural_admixture/tests/test_placeholder.py
neural_admixture/model/__init__.py
neural_admixture/model/train.py
neural_admixture/model/neural_admixture.py
neural_admixture/src/loaders.py
neural_admixture/src/__init__.py
neural_admixture/src/svd.py
neural_admixture/src/utils.py
neural_admixture/src/inference.py
neural_admixture/src/snp_reader.py
neural_admixture/src/main.py
neural_admixture/src/utils_c/rsvd.c
neural_admixture/src/utils_c/rsvd.cpython-312-darwin.so
neural_admixture/src/utils_c/utils.cpython-312-darwin.so
neural_admixture/src/utils_c/pack2bit.cu
neural_admixture/src/utils_c/__int__.py
neural_admixture/src/utils_c/utils.c
neural_admixture/src/utils_c/rsvd.pyx
neural_admixture/src/utils_c/utils.pyx
