Metadata-Version: 2.4
Name: neural-admixture
Version: 1.6.7
Summary: Rapid population clustering with autoencoders
Home-page: https://github.com/AI-sandbox/neural-admixture
Author: Joan Saurina Ricós, Albert Dominguez Mantes
Author-email: joansaurinaricos@gmail.com, adomi@stanford.edu
License: CC BY-NC 4.0
Classifier: Development Status :: 5 - Production/Stable
Classifier: Intended Audience :: Science/Research
Classifier: Topic :: Scientific/Engineering
Classifier: Programming Language :: Python :: 3.10
Classifier: Programming Language :: Python :: 3.11
Classifier: Programming Language :: Python :: 3.12
Classifier: Operating System :: POSIX :: Linux
Classifier: Operating System :: MacOS
Requires-Python: >=3.10
Requires-Dist: configargparse>=1.5.3
Requires-Dist: Cython>=0.29.30
Requires-Dist: numpy>=2.2.5
Requires-Dist: setuptools>=50.3.1
Requires-Dist: torch<=2.4.0,>2.0.0
Requires-Dist: tqdm>=4.64.0
Requires-Dist: scikit-allel>=1.3.5
Requires-Dist: scikit-learn>=1.1.0
Requires-Dist: ninja
Requires-Dist: colorama
Provides-Extra: testing
Requires-Dist: tox; extra == "testing"
Requires-Dist: pytest; extra == "testing"
Requires-Dist: pytest-cov; extra == "testing"
Requires-Dist: pytest-mock; extra == "testing"
